structgen/__init__.py
structgen/cli.py
structgen_cli-0.1.0.dist-info/METADATA
structgen_cli-0.1.0.dist-info/WHEEL
structgen_cli-0.1.0.dist-info/entry_points.txt
structgen_cli-0.1.0.dist-info/top_level.txt
structgen_cli-0.1.0.dist-info/RECORD
