Metadata-Version: 2.4
Name: structgen-cli
Version: 0.1.0
Summary: Generate folder and file structures from pasted tree input
Requires-Python: >=3.8
